hypermat/__init__.py
hypermat/_ad/__init__.py
hypermat/_ad/_deformation.py
hypermat/_calibration/__init__.py
hypermat/_calibration/_load.py
hypermat/_calibration/_utils.py
hypermat/_models/__init__.py
hypermat/_models/_energy.py
hypermat/_models/_material.py
hypermat/_models/_models.py
hypermat/_models/_utils.py
hypermat-0.1.2.dist-info/LICENSE
hypermat-0.1.2.dist-info/METADATA
hypermat-0.1.2.dist-info/WHEEL
hypermat-0.1.2.dist-info/top_level.txt
hypermat-0.1.2.dist-info/RECORD
