Metadata-Version: 2.1
Name: hypermat
Version: 0.1.2
Summary: Hyperelastic formulations using an algorithmic differentiation with hyper-dual numbers in Python
Home-page: https://github.com/ZAARAOUI999/hypermat
Author: Mohamed ZAARAOUI
Author-email: mohamed.zaaraoui.999@gmail.com
License: GNU GENERAL PUBLIC LICENSE
Project-URL: homepage, https://hypermat.readthedocs.io/en/latest
Project-URL: code, https://github.com/ZAARAOUI999/hypermat
Project-URL: issues, https://github.com/ZAARAOUI999/hypermat/issues
Keywords: python,constitution,scientific-computing,fem,finite-elements-analysis,hyperelasticity
Classifier: Development Status :: 5 - Production/Stable
Classifier: Programming Language :: Python
Classifier: Intended Audience :: Science/Research
Classifier: License :: OSI Approved :: GNU General Public License v3 or later (GPLv3+)
Classifier: Operating System :: OS Independent
Classifier: Programming Language :: Python
Classifier: Programming Language :: Python :: 3
Classifier: Programming Language :: Python :: 3.7
Classifier: Programming Language :: Python :: 3.8
Classifier: Programming Language :: Python :: 3.9
Classifier: Programming Language :: Python :: 3.10
Classifier: Programming Language :: Python :: 3.11
Classifier: Topic :: Scientific/Engineering
Classifier: Topic :: Scientific/Engineering :: Mathematics
Classifier: Topic :: Utilities
Requires-Python: >=3.6
License-File: LICENSE
Requires-Dist: numpy
Requires-Dist: matplotlib
Requires-Dist: scipy
Requires-Dist: lmfit
Requires-Dist: tensortrax
